topsis_main/topsis.py
topsis_101703195_finalrevised_finalrevised-0.0.1.dist-info/LICENSE.txt
topsis_101703195_finalrevised_finalrevised-0.0.1.dist-info/METADATA
topsis_101703195_finalrevised_finalrevised-0.0.1.dist-info/WHEEL
topsis_101703195_finalrevised_finalrevised-0.0.1.dist-info/entry_points.txt
topsis_101703195_finalrevised_finalrevised-0.0.1.dist-info/top_level.txt
topsis_101703195_finalrevised_finalrevised-0.0.1.dist-info/RECORD
