Metadata-Version: 2.1
Name: topsis-101703195-finalrevised-finalrevised
Version: 0.0.1
Summary: A Python package implementing TOPSIS technique.
Home-page: UNKNOWN
Author: Gourav Aggarwal
Author-email: gaagarwal_be17@thapar.edu
License: MIT
Platform: UNKNOWN
Classifier: License :: OSI Approved :: MIT License
Classifier: Programming Language :: Python :: 3
Classifier: Programming Language :: Python :: 3.7
Requires-Dist: scipy
Requires-Dist: tabulate
Requires-Dist: numpy
Requires-Dist: pandas
